streamlit_chart_card/__init__.py
streamlit_graphic_card/__init__.py
streamlit_graphic_card/frontend/build/asset-manifest.json
streamlit_graphic_card/frontend/build/bootstrap.min.css
streamlit_graphic_card/frontend/build/index.html
streamlit_graphic_card/frontend/build/precache-manifest.60b9c88a3196c397d6c7738b68d50b3d.js
streamlit_graphic_card/frontend/build/service-worker.js
streamlit_graphic_card/frontend/build/static/js/2.83ebbbbd.chunk.js
streamlit_graphic_card/frontend/build/static/js/2.83ebbbbd.chunk.js.LICENSE.txt
streamlit_graphic_card/frontend/build/static/js/2.83ebbbbd.chunk.js.map
streamlit_graphic_card/frontend/build/static/js/main.9f2319e8.chunk.js
streamlit_graphic_card/frontend/build/static/js/main.9f2319e8.chunk.js.map
streamlit_graphic_card/frontend/build/static/js/runtime-main.44d30fc2.js
streamlit_graphic_card/frontend/build/static/js/runtime-main.44d30fc2.js.map
streamlit_chart_card-0.0.1.dist-info/LICENSE
streamlit_chart_card-0.0.1.dist-info/METADATA
streamlit_chart_card-0.0.1.dist-info/WHEEL
streamlit_chart_card-0.0.1.dist-info/top_level.txt
streamlit_chart_card-0.0.1.dist-info/RECORD
